cyes/__init__.py
cyes/alt.py
cyes/generator.py
cyes/main.py
cyes/reader.py
cyes/states.py
cyes/utils.py
cyes-0.0.3.dist-info/entry_points.txt
cyes-0.0.3.dist-info/LICENSE
cyes-0.0.3.dist-info/WHEEL
cyes-0.0.3.dist-info/METADATA
cyes-0.0.3.dist-info/RECORD
