Metadata-Version: 2.1
Name: cyes
Version: 0.0.3
Summary: C Yet Exist Semicolon - C-like without {;}
Author: ju-djangun
Author-email: ju@djangun.com
Requires-Python: >=3.8,<4.0
Classifier: Programming Language :: Python :: 3
Classifier: Programming Language :: Python :: 3.10
Classifier: Programming Language :: Python :: 3.8
Classifier: Programming Language :: Python :: 3.9
Requires-Dist: anytree (>=2.8.0,<3.0.0)
Requires-Dist: typer[all] (>=0.6.1,<0.7.0)
